FDF/__init__.py
FastDataFile/__init__.py
FastDataFile/classes.py
FastDataFile/encoders.py
FastDataFile/exceptions.py
FastDataFile/methods.py
FastDataFile/worker.py
FastDataFile-2.1.1.dist-info/LICENSE
FastDataFile-2.1.1.dist-info/METADATA
FastDataFile-2.1.1.dist-info/WHEEL
FastDataFile-2.1.1.dist-info/top_level.txt
FastDataFile-2.1.1.dist-info/RECORD
