Metadata-Version: 2.1
Name: FastDataFile
Version: 2.1.1
Summary: The ease of file datafiles
Home-page: https://github.com/ashenguard/fastdatafile
Author: Ashenguard
Author-email: Ashenguard@agmdev.com
License: MIT License
Platform: UNKNOWN
Classifier: Programming Language :: Python :: 3
Classifier: License :: OSI Approved :: MIT License
Classifier: Development Status :: 4 - Beta
Classifier: Operating System :: OS Independent
Requires-Python: >=3.8
Requires-Dist: pyyaml
